changemaker/__init__.py
changemaker/debugger.py
changemaker/generator.py
changemaker/utils/rst.py
changelog_generator-0.7.dist-info/LICENSE
changelog_generator-0.7.dist-info/METADATA
changelog_generator-0.7.dist-info/WHEEL
changelog_generator-0.7.dist-info/entry_points.txt
changelog_generator-0.7.dist-info/top_level.txt
changelog_generator-0.7.dist-info/RECORD
