Metadata-Version: 2.1
Name: changelog-generator
Version: 0.7
Summary: Python module to, generate well formatted commit notes from git commit history.
Author-email: Vignesh Sivanandha Rao <svignesh1793@gmail.com>
License: MIT License
Project-URL: Homepage, https://github.com/thevickypedia/changelog-generator
Project-URL: Docs, https://thevickypedia.github.io/changelog-generator/
Project-URL: Source, https://github.com/thevickypedia/changelog-generator
Project-URL: Bug Tracker, https://github.com/thevickypedia/changelog-generator/issues
Project-URL: Release Notes, https://github.com/thevickypedia/changelog-generator/blob/main/release_notes.rst
Keywords: changelog,automate,commits
Classifier: Development Status :: 5 - Production/Stable
Classifier: Intended Audience :: Developers
Classifier: Operating System :: MacOS :: MacOS X
Classifier: License :: OSI Approved :: MIT License
Classifier: Programming Language :: Python :: 3.9
Classifier: Topic :: Software Development :: Version Control :: Git
Classifier: Programming Language :: Python :: 3.7
Classifier: Programming Language :: Python :: 3.8
Classifier: Programming Language :: Python :: 3.9
Classifier: Programming Language :: Python :: 3.10
Classifier: Programming Language :: Python :: 3.11
Classifier: Operating System :: MacOS :: MacOS X
Classifier: Operating System :: Microsoft :: Windows :: Windows 10
Classifier: Operating System :: Microsoft :: Windows :: Windows 11
Classifier: Topic :: Documentation :: Sphinx
Requires-Python: >=3.7
License-File: LICENSE
Requires-Dist: click
Provides-Extra: dev
Requires-Dist: pre-commit ; extra == 'dev'
Requires-Dist: xmltodict ; extra == 'dev'
